py_chinese_pronounce/CNS2UNICODE_Unicode BMP.txt
py_chinese_pronounce/CNS_phonetic.txt
py_chinese_pronounce/CNS_pinyin_1.txt
py_chinese_pronounce/CNS_pinyin_2.txt
py_chinese_pronounce/__init__.py
py_chinese_pronounce/core.py
py_chinese_pronounce/dict_concised_2014_20230112.xlsx
py_chinese_pronounce/dict_concised_2014_20240705.xlsx
py_chinese_pronounce/sc-dict.txt
py_chinese_pronounce-0.1.14.dist-info/METADATA
py_chinese_pronounce-0.1.14.dist-info/WHEEL
py_chinese_pronounce-0.1.14.dist-info/RECORD
