Metadata-Version: 2.1
Name: py-chinese-pronounce
Version: 0.1.14
Summary: 文字/漢語發音/注音互轉。相似發聲字/單詞。
Home-page: https://github.com/p208p2002/py-chinese-pronounce
Author: Philip Huang
Author-email: p208p2002@gmail.com
Requires-Python: >=3.8.0,<4.0.0
Classifier: Programming Language :: Python :: 3
Classifier: Programming Language :: Python :: 3.8
Classifier: Programming Language :: Python :: 3.9
Classifier: Programming Language :: Python :: 3.10
Classifier: Programming Language :: Python :: 3.11
Classifier: Programming Language :: Python :: 3.12
Requires-Dist: Levenshtein (>=0.20.5,<0.21.0)
Requires-Dist: ahocorasick-python (>=0.0.9,<0.0.10)
Requires-Dist: openpyxl (>=3.1.2,<4.0.0)
Requires-Dist: pandas (>=1.5.3,<2.0.0)
Requires-Dist: xlrd (>=2.0.1,<3.0.0)
